[{"acc_x": 0.1584, "acc_y": 0.9411, "acc_z": -0.3311, "gy_x": 15.9562, "gy_y": 125.8925, "gy_z": 6.5029, "timestamp": "1676159094.1375"}, {"acc_x": 0.1394, "acc_y": 0.9537, "acc_z": -0.3437, "gy_x": 16.1151, "gy_y": 125.3629, "gy_z": 7.0657, "timestamp": "1676159094.15"}, {"acc_x": 0.1116, "acc_y": 0.9735, "acc_z": -0.3484, "gy_x": 17.7637, "gy_y": 124.7389, "gy_z": 7.2268, "timestamp": "1676159094.1625"}, {"acc_x": 0.1093, "acc_y": 0.9393, "acc_z": -0.3396, "gy_x": 18.6512, "gy_y": 124.7956, "gy_z": 7.2285, "timestamp": "1676159094.175"}, {"acc_x": 0.0967, "acc_y": 0.9267, "acc_z": -0.3334, "gy_x": 19.5386, "gy_y": 124.9662, "gy_z": 7.1493, "timestamp": "1676159094.1875"}, {"acc_x": 0.1403, "acc_y": 0.9197, "acc_z": -0.3248, "gy_x": 20.1544, "gy_y": 124.7309, "gy_z": 6.8856, "timestamp": "1676159094.2"}, {"acc_x": 0.1422, "acc_y": 0.9178, "acc_z": -0.3355, "gy_x": 20.5055, "gy_y": 124.3415, "gy_z": 6.5345, "timestamp": "1676159094.2125"}, {"acc_x": 0.1609, "acc_y": 0.9519, "acc_z": -0.33, "gy_x": 21.7898, "gy_y": 123.41, "gy_z": 5.49, "timestamp": "1676159094.225"}, {"acc_x": 0.1673, "acc_y": 0.9673, "acc_z": -0.3273, "gy_x": 21.95, "gy_y": 123.6566, "gy_z": 5.45, "timestamp": "1676159094.2375"}, {"acc_x": 0.1544, "acc_y": 0.96, "acc_z": -0.3144, "gy_x": 22.7428, "gy_y": 123.6656, "gy_z": 5.6361, "timestamp": "1676159094.25"}, {"acc_x": 0.15, "acc_y": 0.9774, "acc_z": -0.31, "gy_x": 22.7547, "gy_y": 123.6671, "gy_z": 5.7624, "timestamp": "1676159094.2625"}, {"acc_x": 0.15, "acc_y": 0.99, "acc_z": -0.31, "gy_x": 22.83, "gy_y": 123.7677, "gy_z": 5.8183, "timestamp": "1676159094.275"}, {"acc_x": 0.1628, "acc_y": 1.0057, "acc_z": -0.31, "gy_x": 22.8318, "gy_y": 123.4795, "gy_z": 6.5543, "timestamp": "1676159094.2875"}, {"acc_x": 0.1753, "acc_y": 1.02, "acc_z": -0.31, "gy_x": 22.5661, "gy_y": 123.5227, "gy_z": 6.6656, "timestamp": "1676159094.3"}, {"acc_x": 0.18, "acc_y": 1.02, "acc_z": -0.31, "gy_x": 22.89, "gy_y": 124.2965, "gy_z": 7.3413, "timestamp": "1676159094.3125"}, {"acc_x": 0.1805, "acc_y": 1.0395, "acc_z": -0.31, "gy_x": 22.3247, "gy_y": 124.39, "gy_z": 7.6658, "timestamp": "1676159094.325"}, {"acc_x": 0.19, "acc_y": 1.03, "acc_z": -0.3071, "gy_x": 22.6806, "gy_y": 139.0584, "gy_z": 9.2656, "timestamp": "1676159094.3375"}, {"acc_x": 0.19, "acc_y": 1.0359, "acc_z": -0.2941, "gy_x": 22.4717, "gy_y": 128.821, "gy_z": 9.5891, "timestamp": "1676159094.35"}, {"acc_x": 0.19, "acc_y": 1.0484, "acc_z": -0.2816, "gy_x": 22.2173, "gy_y": 125.7211, "gy_z": 10.1644, "timestamp": "1676159094.3625"}, {"acc_x": 0.21, "acc_y": 1.04, "acc_z": -0.27, "gy_x": 22.0305, "gy_y": 125.9795, "gy_z": 11.7742, "timestamp": "1676159094.375"}, {"acc_x": 0.21, "acc_y": 1.04, "acc_z": -0.27, "gy_x": 21.6916, "gy_y": 126.0057, "gy_z": 12.067, "timestamp": "1676159094.3875"}, {"acc_x": 0.21, "acc_y": 1.04, "acc_z": -0.27, "gy_x": 21.3522, "gy_y": 126.0315, "gy_z": 12.3549, "timestamp": "1676159094.4"}, {"acc_x": 0.2019, "acc_y": 1.04, "acc_z": -0.28, "gy_x": 20.7249, "gy_y": 125.9081, "gy_z": 14.0311, "timestamp": "1676159094.4125"}, {"acc_x": 0.1999, "acc_y": 1.0301, "acc_z": -0.2701, "gy_x": 19.4729, "gy_y": 125.6281, "gy_z": 15.3215, "timestamp": "1676159094.425"}, {"acc_x": 0.191, "acc_y": 1.049, "acc_z": -0.279, "gy_x": 20.4177, "gy_y": 125.7527, "gy_z": 15.927, "timestamp": "1676159094.4375"}, {"acc_x": 0.1951, "acc_y": 1.0449, "acc_z": -0.2749, "gy_x": 19.7992, "gy_y": 125.6012, "gy_z": 16.1584, "timestamp": "1676159094.45"}, {"acc_x": 0.1991, "acc_y": 1.0409, "acc_z": -0.2709, "gy_x": 19.1807, "gy_y": 125.4498, "gy_z": 16.3898, "timestamp": "1676159094.4625"}, {"acc_x": 0.21, "acc_y": 1.05, "acc_z": -0.26, "gy_x": 19.7808, "gy_y": 125.2812, "gy_z": 18.6566, "timestamp": "1676159094.475"}, {"acc_x": 0.2066, "acc_y": 1.0534, "acc_z": -0.2566, "gy_x": 18.5506, "gy_y": 124.4518, "gy_z": 21.1479, "timestamp": "1676159094.4875"}, {"acc_x": 0.1943, "acc_y": 1.0543, "acc_z": -0.25, "gy_x": 18.7245, "gy_y": 124.2055, "gy_z": 21.7829, "timestamp": "1676159094.5"}, {"acc_x": 0.1825, "acc_y": 1.05, "acc_z": -0.2425, "gy_x": 18.6855, "gy_y": 124.0428, "gy_z": 22.219, "timestamp": "1676159094.5125"}, {"acc_x": 0.1688, "acc_y": 1.05, "acc_z": -0.2388, "gy_x": 17.1637, "gy_y": 122.6868, "gy_z": 23.8097, "timestamp": "1676159094.525"}, {"acc_x": 0.1547, "acc_y": 1.0526, "acc_z": -0.23, "gy_x": 17.7102, "gy_y": 122.9601, "gy_z": 24.1974, "timestamp": "1676159094.5375"}, {"acc_x": 0.1351, "acc_y": 1.0551, "acc_z": -0.2251, "gy_x": 16.5424, "gy_y": 122.6767, "gy_z": 25.5717, "timestamp": "1676159094.55"}, {"acc_x": 0.1223, "acc_y": 1.0577, "acc_z": -0.2123, "gy_x": 16.3843, "gy_y": 123.0456, "gy_z": 26.0185, "timestamp": "1676159094.5625"}, {"acc_x": 0.0998, "acc_y": 1.0602, "acc_z": -0.1998, "gy_x": 15.8534, "gy_y": 123.23, "gy_z": 26.4835, "timestamp": "1676159094.575"}, {"acc_x": 0.0882, "acc_y": 1.07, "acc_z": -0.1882, "gy_x": 13.8098, "gy_y": 123.2819, "gy_z": 26.8506, "timestamp": "1676159094.5875"}, {"acc_x": 0.0819, "acc_y": 1.07, "acc_z": -0.1819, "gy_x": 12.7381, "gy_y": 123.2443, "gy_z": 26.8067, "timestamp": "1676159094.6"}, {"acc_x": 0.0247, "acc_y": 1.0193, "acc_z": -0.1278, "gy_x": 13.6265, "gy_y": 124.1239, "gy_z": 26.1722, "timestamp": "1676159094.6125"}, {"acc_x": 0.0188, "acc_y": 1.0023, "acc_z": -0.11, "gy_x": 14.2384, "gy_y": 124.1307, "gy_z": 25.7683, "timestamp": "1676159094.625"}, {"acc_x": 0.01, "acc_y": 1.0141, "acc_z": -0.107, "gy_x": 11.4829, "gy_y": 122.6284, "gy_z": 24.6047, "timestamp": "1676159094.6375"}, {"acc_x": 0.01, "acc_y": 1.0, "acc_z": -0.0941, "gy_x": 12.2713, "gy_y": 122.0604, "gy_z": 23.8603, "timestamp": "1676159094.65"}, {"acc_x": 0.0024, "acc_y": 0.9849, "acc_z": -0.0749, "gy_x": 11.1961, "gy_y": 121.2589, "gy_z": 23.3846, "timestamp": "1676159094.6625"}, {"acc_x": -0.0034, "acc_y": 0.9664, "acc_z": -0.0598, "gy_x": 10.5172, "gy_y": 119.4455, "gy_z": 20.6996, "timestamp": "1676159094.675"}, {"acc_x": -0.0078, "acc_y": 0.9489, "acc_z": -0.0467, "gy_x": 10.8896, "gy_y": 119.0212, "gy_z": 20.1973, "timestamp": "1676159094.6875"}, {"acc_x": -0.0378, "acc_y": 0.8957, "acc_z": -0.0157, "gy_x": 11.2672, "gy_y": 118.3173, "gy_z": 19.4681, "timestamp": "1676159094.7"}, {"acc_x": -0.0312, "acc_y": 0.8824, "acc_z": -0.0024, "gy_x": 11.6526, "gy_y": 117.2078, "gy_z": 18.4094, "timestamp": "1676159094.7125"}, {"acc_x": -0.0294, "acc_y": 0.8606, "acc_z": 0.0506, "gy_x": 11.8104, "gy_y": 116.0044, "gy_z": 17.3377, "timestamp": "1676159094.725"}, {"acc_x": -0.0158, "acc_y": 0.8714, "acc_z": 0.0558, "gy_x": 7.3103, "gy_y": 112.8794, "gy_z": 16.0002, "timestamp": "1676159094.7375"}, {"acc_x": 0.0028, "acc_y": 0.8776, "acc_z": 0.0372, "gy_x": 4.5241, "gy_y": 110.7842, "gy_z": 14.9964, "timestamp": "1676159094.75"}, {"acc_x": 0.02, "acc_y": 0.87, "acc_z": 0.0662, "gy_x": 3.1705, "gy_y": 107.759, "gy_z": 14.3106, "timestamp": "1676159094.7625"}, {"acc_x": 0.0213, "acc_y": 0.8206, "acc_z": 0.1, "gy_x": 2.3072, "gy_y": 106.2441, "gy_z": 14.16, "timestamp": "1676159094.775"}, {"acc_x": 0.04, "acc_y": 0.8269, "acc_z": 0.1, "gy_x": 1.6285, "gy_y": 104.2289, "gy_z": 14.258, "timestamp": "1676159094.7875"}, {"acc_x": 0.0429, "acc_y": 0.8257, "acc_z": 0.1, "gy_x": 0.8815, "gy_y": 102.7402, "gy_z": 14.4309, "timestamp": "1676159094.8"}, {"acc_x": 0.0489, "acc_y": 0.8378, "acc_z": 0.1, "gy_x": 0.324, "gy_y": 102.001, "gy_z": 14.5096, "timestamp": "1676159094.8125"}, {"acc_x": 0.0593, "acc_y": 0.8807, "acc_z": 0.0833, "gy_x": -1.0294, "gy_y": 100.1023, "gy_z": 14.9467, "timestamp": "1676159094.825"}, {"acc_x": 0.0589, "acc_y": 0.89, "acc_z": 0.13, "gy_x": -1.6608, "gy_y": 98.6456, "gy_z": 15.303, "timestamp": "1676159094.8375"}, {"acc_x": 0.08, "acc_y": 0.8954, "acc_z": 0.1193, "gy_x": -2.4374, "gy_y": 95.4779, "gy_z": 15.8685, "timestamp": "1676159094.85"}, {"acc_x": 0.08, "acc_y": 0.9, "acc_z": 0.118, "gy_x": -2.87, "gy_y": 93.6399, "gy_z": 16.026, "timestamp": "1676159094.8625"}, {"acc_x": 0.09, "acc_y": 0.89, "acc_z": 0.1399, "gy_x": -3.0205, "gy_y": 91.0845, "gy_z": 16.17, "timestamp": "1676159094.875"}, {"acc_x": 0.1231, "acc_y": 0.9037, "acc_z": 0.1563, "gy_x": -3.6727, "gy_y": 85.4185, "gy_z": 16.0027, "timestamp": "1676159094.8875"}, {"acc_x": 0.13, "acc_y": 0.8272, "acc_z": 0.1072, "gy_x": -3.7487, "gy_y": 83.7984, "gy_z": 16.0787, "timestamp": "1676159094.9"}, {"acc_x": 0.1531, "acc_y": 0.9007, "acc_z": 0.1192, "gy_x": -5.6959, "gy_y": 79.5896, "gy_z": 16.4984, "timestamp": "1676159094.9125"}, {"acc_x": 0.16, "acc_y": 0.8549, "acc_z": 0.1637, "gy_x": -5.3702, "gy_y": 78.4125, "gy_z": 17.0052, "timestamp": "1676159094.925"}, {"acc_x": 0.1686, "acc_y": 0.8929, "acc_z": 0.19, "gy_x": -4.6321, "gy_y": 74.2, "gy_z": 17.139, "timestamp": "1676159094.9375"}, {"acc_x": 0.2075, "acc_y": 0.8942, "acc_z": 0.1842, "gy_x": -5.3118, "gy_y": 69.3703, "gy_z": 17.0128, "timestamp": "1676159094.95"}, {"acc_x": 0.2046, "acc_y": 0.8746, "acc_z": 0.203, "gy_x": -5.7998, "gy_y": 67.4919, "gy_z": 16.8056, "timestamp": "1676159094.9625"}, {"acc_x": 0.2003, "acc_y": 0.8922, "acc_z": 0.22, "gy_x": -6.6009, "gy_y": 61.4262, "gy_z": 15.6772, "timestamp": "1676159094.975"}, {"acc_x": 0.184, "acc_y": 0.9513, "acc_z": 0.2171, "gy_x": -7.0504, "gy_y": 60.0348, "gy_z": 15.1477, "timestamp": "1676159094.9875"}, {"acc_x": 0.1307, "acc_y": 0.9086, "acc_z": 0.2154, "gy_x": -6.8681, "gy_y": 54.6545, "gy_z": 13.9075, "timestamp": "1676159095.0"}, {"acc_x": 0.2212, "acc_y": 0.8738, "acc_z": 0.2119, "gy_x": -7.1999, "gy_y": 50.8331, "gy_z": 13.2087, "timestamp": "1676159095.0125"}, {"acc_x": 0.2242, "acc_y": 0.891, "acc_z": 0.2205, "gy_x": -7.4095, "gy_y": 47.9379, "gy_z": 12.2978, "timestamp": "1676159095.025"}, {"acc_x": 0.2189, "acc_y": 0.907, "acc_z": 0.227, "gy_x": -7.32, "gy_y": 41.8809, "gy_z": 10.0124, "timestamp": "1676159095.0375"}, {"acc_x": 0.2263, "acc_y": 0.9, "acc_z": 0.209, "gy_x": -7.32, "gy_y": 37.207, "gy_z": 8.4677, "timestamp": "1676159095.05"}, {"acc_x": 0.1954, "acc_y": 0.9, "acc_z": 0.1843, "gy_x": -6.5537, "gy_y": 33.8498, "gy_z": 6.9661, "timestamp": "1676159095.0625"}, {"acc_x": 0.2271, "acc_y": 0.9793, "acc_z": 0.2104, "gy_x": -5.2095, "gy_y": 31.1954, "gy_z": 5.5522, "timestamp": "1676159095.075"}, {"acc_x": 0.1778, "acc_y": 0.967, "acc_z": 0.2165, "gy_x": -3.83, "gy_y": 28.5408, "gy_z": 4.1518, "timestamp": "1676159095.0875"}, {"acc_x": 0.1609, "acc_y": 0.9709, "acc_z": 0.2255, "gy_x": -6.7052, "gy_y": 22.7329, "gy_z": 1.9322, "timestamp": "1676159095.1"}, {"acc_x": 0.1554, "acc_y": 0.9727, "acc_z": 0.2446, "gy_x": -7.0297, "gy_y": 20.0634, "gy_z": 0.8393, "timestamp": "1676159095.1125"}, {"acc_x": 0.1288, "acc_y": 0.98, "acc_z": 0.24, "gy_x": -7.0189, "gy_y": 16.0838, "gy_z": -1.4163, "timestamp": "1676159095.125"}, {"acc_x": 0.1142, "acc_y": 0.98, "acc_z": 0.24, "gy_x": -6.9429, "gy_y": 14.2284, "gy_z": -2.5752, "timestamp": "1676159095.1375"}, {"acc_x": 0.0949, "acc_y": 0.98, "acc_z": 0.2298, "gy_x": -7.3009, "gy_y": 12.3477, "gy_z": -3.4787, "timestamp": "1676159095.15"}, {"acc_x": 0.086, "acc_y": 0.98, "acc_z": 0.22, "gy_x": -7.4331, "gy_y": 10.1544, "gy_z": -4.5556, "timestamp": "1676159095.1625"}, {"acc_x": 0.08, "acc_y": 0.9802, "acc_z": 0.2198, "gy_x": -7.2207, "gy_y": 9.7525, "gy_z": -4.9509, "timestamp": "1676159095.175"}, {"acc_x": 0.08, "acc_y": 1.012, "acc_z": 0.1819, "gy_x": -8.73, "gy_y": 8.1024, "gy_z": -5.9947, "timestamp": "1676159095.1875"}, {"acc_x": 0.0855, "acc_y": 1.0255, "acc_z": 0.1445, "gy_x": -8.73, "gy_y": 7.8417, "gy_z": -6.2131, "timestamp": "1676159095.2"}, {"acc_x": 0.0779, "acc_y": 1.0542, "acc_z": 0.1481, "gy_x": -11.6847, "gy_y": 5.791, "gy_z": -7.3316, "timestamp": "1676159095.2125"}, {"acc_x": 0.0605, "acc_y": 1.0875, "acc_z": 0.16, "gy_x": -12.3799, "gy_y": 5.4582, "gy_z": -7.5633, "timestamp": "1676159095.225"}, {"acc_x": 0.0675, "acc_y": 1.0425, "acc_z": 0.1575, "gy_x": -8.8829, "gy_y": 5.8834, "gy_z": -8.0171, "timestamp": "1676159095.2375"}, {"acc_x": 0.0441, "acc_y": 1.05, "acc_z": 0.1553, "gy_x": -8.564, "gy_y": 5.2417, "gy_z": -8.5769, "timestamp": "1676159095.25"}, {"acc_x": 0.03, "acc_y": 1.0422, "acc_z": 0.1522, "gy_x": -8.9099, "gy_y": 4.9336, "gy_z": -8.8095, "timestamp": "1676159095.2625"}, {"acc_x": -0.0008, "acc_y": 1.0192, "acc_z": 0.1292, "gy_x": -7.9386, "gy_y": 4.82, "gy_z": -10.179, "timestamp": "1676159095.275"}, {"acc_x": -0.0071, "acc_y": 1.01, "acc_z": 0.1229, "gy_x": -7.4609, "gy_y": 4.5437, "gy_z": -10.3507, "timestamp": "1676159095.2875"}, {"acc_x": 0.0053, "acc_y": 0.9995, "acc_z": 0.13, "gy_x": -6.3513, "gy_y": 4.299, "gy_z": -10.7077, "timestamp": "1676159095.3"}, {"acc_x": 0.01, "acc_y": 0.9551, "acc_z": 0.13, "gy_x": -5.5992, "gy_y": 4.354, "gy_z": -11.0502, "timestamp": "1676159095.3125"}, {"acc_x": 0.0198, "acc_y": 0.9598, "acc_z": 0.1298, "gy_x": -5.0658, "gy_y": 3.884, "gy_z": -11.5692, "timestamp": "1676159095.325"}, {"acc_x": 0.0067, "acc_y": 0.9483, "acc_z": 0.12, "gy_x": -4.4845, "gy_y": 3.78, "gy_z": -12.2306, "timestamp": "1676159095.3375"}, {"acc_x": -0.0059, "acc_y": 0.9421, "acc_z": 0.12, "gy_x": -4.2898, "gy_y": 3.78, "gy_z": -12.3437, "timestamp": "1676159095.35"}, {"acc_x": -0.01, "acc_y": 0.9231, "acc_z": 0.1031, "gy_x": -2.81, "gy_y": 4.03, "gy_z": -12.3064, "timestamp": "1676159095.3625"}, {"acc_x": -0.0094, "acc_y": 0.9294, "acc_z": 0.11, "gy_x": -2.81, "gy_y": 4.03, "gy_z": -12.2513, "timestamp": "1676159095.375"}, {"acc_x": 0.0048, "acc_y": 0.92, "acc_z": 0.11, "gy_x": -2.3801, "gy_y": 4.5788, "gy_z": -11.3507, "timestamp": "1676159095.3875"}, {"acc_x": 0.0425, "acc_y": 0.9256, "acc_z": 0.1044, "gy_x": -1.6507, "gy_y": 5.0, "gy_z": -10.5719, "timestamp": "1676159095.4"}, {"acc_x": 0.06, "acc_y": 0.9455, "acc_z": 0.1, "gy_x": -1.9533, "gy_y": 5.0, "gy_z": -10.3008, "timestamp": "1676159095.4125"}, {"acc_x": 0.0522, "acc_y": 0.98, "acc_z": 0.1011, "gy_x": -3.4141, "gy_y": 4.027, "gy_z": -9.6335, "timestamp": "1676159095.425"}, {"acc_x": 0.0758, "acc_y": 0.9742, "acc_z": 0.1129, "gy_x": -3.0126, "gy_y": 3.823, "gy_z": -9.1925, "timestamp": "1676159095.4375"}, {"acc_x": 0.0954, "acc_y": 0.9707, "acc_z": 0.1093, "gy_x": -2.2985, "gy_y": 2.6577, "gy_z": -7.3894, "timestamp": "1676159095.45"}, {"acc_x": 0.1164, "acc_y": 0.9964, "acc_z": 0.1, "gy_x": -3.3242, "gy_y": 0.8579, "gy_z": -5.9809, "timestamp": "1676159095.4625"}, {"acc_x": 0.1308, "acc_y": 1.0108, "acc_z": 0.0946, "gy_x": -3.5419, "gy_y": -0.0583, "gy_z": -5.297, "timestamp": "1676159095.475"}, {"acc_x": 0.1552, "acc_y": 1.0174, "acc_z": 0.0379, "gy_x": -4.0009, "gy_y": -1.5165, "gy_z": -4.4212, "timestamp": "1676159095.4875"}, {"acc_x": 0.1134, "acc_y": 1.027, "acc_z": 0.094, "gy_x": -3.4599, "gy_y": -2.5928, "gy_z": -3.8449, "timestamp": "1676159095.5"}, {"acc_x": 0.0954, "acc_y": 1.0146, "acc_z": 0.0861, "gy_x": -5.4892, "gy_y": -6.43, "gy_z": -1.8084, "timestamp": "1676159095.5125"}, {"acc_x": 0.1, "acc_y": 0.9784, "acc_z": 0.07, "gy_x": -5.7085, "gy_y": -7.3387, "gy_z": -0.9929, "timestamp": "1676159095.525"}, {"acc_x": 0.0931, "acc_y": 0.9477, "acc_z": 0.0654, "gy_x": -6.7576, "gy_y": -8.9179, "gy_z": 0.4836, "timestamp": "1676159095.5375"}, {"acc_x": 0.0584, "acc_y": 0.9342, "acc_z": 0.05, "gy_x": -6.3754, "gy_y": -9.9906, "gy_z": 1.0394, "timestamp": "1676159095.55"}, {"acc_x": 0.0577, "acc_y": 0.9223, "acc_z": 0.0346, "gy_x": -7.4381, "gy_y": -10.933, "gy_z": 1.3602, "timestamp": "1676159095.5625"}, {"acc_x": 0.059, "acc_y": 0.9032, "acc_z": 0.031, "gy_x": -8.0027, "gy_y": -12.1497, "gy_z": 3.0476, "timestamp": "1676159095.575"}, {"acc_x": 0.1266, "acc_y": 1.0251, "acc_z": 0.0528, "gy_x": -8.6388, "gy_y": -13.0324, "gy_z": 3.3727, "timestamp": "1676159095.5875"}, {"acc_x": 0.0099, "acc_y": 2.6806, "acc_z": 0.0464, "gy_x": -36.7416, "gy_y": -18.7354, "gy_z": -0.5105, "timestamp": "1676159095.6"}, {"acc_x": -0.5751, "acc_y": 1.8843, "acc_z": 0.1708, "gy_x": -30.1718, "gy_y": -19.0069, "gy_z": -8.5431, "timestamp": "1676159095.6125"}, {"acc_x": -0.7686, "acc_y": 2.1596, "acc_z": 0.9693, "gy_x": 25.6064, "gy_y": -12.2875, "gy_z": -13.4929, "timestamp": "1676159095.625"}, {"acc_x": 0.098, "acc_y": 0.5206, "acc_z": 0.0905, "gy_x": 29.2089, "gy_y": 8.8503, "gy_z": 0.9341, "timestamp": "1676159095.6375"}, {"acc_x": 0.0966, "acc_y": 0.9504, "acc_z": 0.1127, "gy_x": 13.2692, "gy_y": -0.9544, "gy_z": -0.6969, "timestamp": "1676159095.65"}, {"acc_x": 0.1465, "acc_y": 1.0796, "acc_z": 0.1148, "gy_x": -0.3424, "gy_y": -4.8272, "gy_z": -3.4466, "timestamp": "1676159095.6625"}, {"acc_x": 0.1876, "acc_y": 1.1259, "acc_z": 0.1435, "gy_x": -0.4988, "gy_y": -4.4471, "gy_z": -2.5878, "timestamp": "1676159095.675"}, {"acc_x": 0.0629, "acc_y": 0.8371, "acc_z": 0.13, "gy_x": 24.246, "gy_y": 2.0496, "gy_z": -0.85, "timestamp": "1676159095.6875"}, {"acc_x": 0.0344, "acc_y": 0.9159, "acc_z": 0.1244, "gy_x": 22.9563, "gy_y": 1.7341, "gy_z": -0.6713, "timestamp": "1676159095.7"}, {"acc_x": 0.046, "acc_y": 0.968, "acc_z": 0.0318, "gy_x": 18.0986, "gy_y": -0.9718, "gy_z": -0.1953, "timestamp": "1676159095.7125"}, {"acc_x": 0.0676, "acc_y": 0.9524, "acc_z": 0.0124, "gy_x": 22.092, "gy_y": -1.9072, "gy_z": 0.1181, "timestamp": "1676159095.725"}, {"acc_x": 0.1414, "acc_y": 0.9591, "acc_z": 0.3359, "gy_x": 23.7986, "gy_y": -1.3401, "gy_z": 0.0035, "timestamp": "1676159095.7375"}, {"acc_x": 0.1176, "acc_y": 1.1444, "acc_z": 0.6178, "gy_x": -2.2632, "gy_y": -3.7224, "gy_z": 2.9621, "timestamp": "1676159095.75"}, {"acc_x": 0.0046, "acc_y": 0.3685, "acc_z": -0.1501, "gy_x": -13.5981, "gy_y": -0.9889, "gy_z": 1.8355, "timestamp": "1676159095.7625"}, {"acc_x": -0.0687, "acc_y": 0.8787, "acc_z": -0.096, "gy_x": -27.1917, "gy_y": 0.4501, "gy_z": -0.4635, "timestamp": "1676159095.775"}, {"acc_x": 0.0359, "acc_y": 1.0993, "acc_z": -0.0215, "gy_x": -20.7006, "gy_y": 0.5513, "gy_z": -1.1625, "timestamp": "1676159095.7875"}, {"acc_x": 0.0649, "acc_y": 1.0547, "acc_z": 0.035, "gy_x": -6.8274, "gy_y": 1.7465, "gy_z": -1.4841, "timestamp": "1676159095.8"}, {"acc_x": 0.0891, "acc_y": 0.9791, "acc_z": 0.1485, "gy_x": -2.3084, "gy_y": -4.2179, "gy_z": 0.3787, "timestamp": "1676159095.8125"}, {"acc_x": -0.0329, "acc_y": 1.3152, "acc_z": 0.2217, "gy_x": -10.5653, "gy_y": -6.9647, "gy_z": 0.4963, "timestamp": "1676159095.825"}, {"acc_x": -0.0636, "acc_y": 0.9357, "acc_z": 0.2289, "gy_x": 17.8842, "gy_y": 4.3238, "gy_z": -0.1822, "timestamp": "1676159095.8375"}, {"acc_x": -0.0262, "acc_y": 1.047, "acc_z": 0.16, "gy_x": -7.071, "gy_y": -3.5375, "gy_z": -0.7144, "timestamp": "1676159095.85"}, {"acc_x": -0.055, "acc_y": 1.055, "acc_z": 0.1375, "gy_x": -11.9481, "gy_y": -5.268, "gy_z": -0.985, "timestamp": "1676159095.8625"}, {"acc_x": -0.0589, "acc_y": 0.9694, "acc_z": 0.1222, "gy_x": 4.234, "gy_y": -1.2166, "gy_z": -0.7328, "timestamp": "1676159095.875"}, {"acc_x": -0.032, "acc_y": 0.9707, "acc_z": 0.16, "gy_x": 7.8701, "gy_y": 0.8521, "gy_z": -0.7672, "timestamp": "1676159095.8875"}, {"acc_x": 0.003, "acc_y": 0.9978, "acc_z": 0.1492, "gy_x": -4.1143, "gy_y": 0.0239, "gy_z": -0.7387, "timestamp": "1676159095.9"}, {"acc_x": 0.0423, "acc_y": 0.9913, "acc_z": 0.1164, "gy_x": -1.7912, "gy_y": 0.8245, "gy_z": -0.7649, "timestamp": "1676159095.9125"}, {"acc_x": 0.0596, "acc_y": 0.99, "acc_z": 0.1291, "gy_x": 0.3526, "gy_y": 1.5035, "gy_z": -0.787, "timestamp": "1676159095.925"}, {"acc_x": 0.06, "acc_y": 0.9911, "acc_z": 0.11, "gy_x": -0.6417, "gy_y": -0.01, "gy_z": -0.7373, "timestamp": "1676159095.9375"}, {"acc_x": 0.0546, "acc_y": 0.9915, "acc_z": 0.1261, "gy_x": 1.9418, "gy_y": 0.6104, "gy_z": -0.7782, "timestamp": "1676159095.95"}, {"acc_x": 0.0847, "acc_y": 0.9666, "acc_z": 0.1139, "gy_x": -1.0478, "gy_y": -0.3112, "gy_z": -0.488, "timestamp": "1676159095.9625"}, {"acc_x": 0.0164, "acc_y": 0.9722, "acc_z": 0.0893, "gy_x": 1.4404, "gy_y": 0.3967, "gy_z": -0.4601, "timestamp": "1676159095.975"}, {"acc_x": -0.03, "acc_y": 1.0, "acc_z": 0.0876, "gy_x": -1.0348, "gy_y": 0.2482, "gy_z": -0.3516, "timestamp": "1676159095.9875"}, {"acc_x": -0.03, "acc_y": 0.9892, "acc_z": 0.11, "gy_x": -3.8011, "gy_y": -0.2677, "gy_z": -0.211, "timestamp": "1676159096.0"}, {"acc_x": 0.0073, "acc_y": 0.98, "acc_z": 0.1025, "gy_x": -1.4634, "gy_y": 0.3104, "gy_z": -0.1356, "timestamp": "1676159096.0125"}, {"acc_x": 0.04, "acc_y": 0.98, "acc_z": 0.1203, "gy_x": 0.5111, "gy_y": 0.0052, "gy_z": -0.12, "timestamp": "1676159096.025"}, {"acc_x": 0.04, "acc_y": 0.98, "acc_z": 0.1264, "gy_x": 1.0426, "gy_y": -0.023, "gy_z": -0.083, "timestamp": "1676159096.0375"}, {"acc_x": 0.0555, "acc_y": 0.99, "acc_z": 0.13, "gy_x": 1.1981, "gy_y": -0.2009, "gy_z": -0.1058, "timestamp": "1676159096.05"}, {"acc_x": 0.0425, "acc_y": 0.99, "acc_z": 0.1262, "gy_x": 0.5422, "gy_y": -0.7039, "gy_z": -0.2204, "timestamp": "1676159096.0625"}, {"acc_x": 0.0302, "acc_y": 0.99, "acc_z": 0.1201, "gy_x": -0.0515, "gy_y": -1.2715, "gy_z": -0.3088, "timestamp": "1676159096.075"}, {"acc_x": -0.01, "acc_y": 0.99, "acc_z": 0.12, "gy_x": -0.5098, "gy_y": -1.6625, "gy_z": -0.43, "timestamp": "1676159096.0875"}, {"acc_x": -0.0073, "acc_y": 0.99, "acc_z": 0.1227, "gy_x": -0.0149, "gy_y": -1.4278, "gy_z": -0.43, "timestamp": "1676159096.1"}, {"acc_x": -0.0013, "acc_y": 0.99, "acc_z": 0.1287, "gy_x": 0.4799, "gy_y": -1.1932, "gy_z": -0.43, "timestamp": "1676159096.1125"}, {"acc_x": 0.0, "acc_y": 0.9849, "acc_z": 0.1351, "gy_x": 0.9641, "gy_y": -0.7965, "gy_z": -0.43, "timestamp": "1676159096.125"}]