[{"acc_x": 0.0108, "acc_y": 0.9884, "acc_z": 0.1108, "gy_x": 0.0497, "gy_y": 0.3459, "gy_z": -0.228, "timestamp": "1676156574.0"}, {"acc_x": 0.0166, "acc_y": 0.97, "acc_z": 0.1166, "gy_x": 2.1719, "gy_y": 1.0894, "gy_z": -0.195, "timestamp": "1676156574.0125"}, {"acc_x": 0.012, "acc_y": 0.9761, "acc_z": 0.1141, "gy_x": 1.62, "gy_y": 0.8264, "gy_z": -0.2511, "timestamp": "1676156574.025"}, {"acc_x": 0.0162, "acc_y": 0.9887, "acc_z": 0.1225, "gy_x": 1.0682, "gy_y": 0.5634, "gy_z": -0.3071, "timestamp": "1676156574.0375"}, {"acc_x": 0.02, "acc_y": 0.9988, "acc_z": 0.1276, "gy_x": 0.3074, "gy_y": 0.3039, "gy_z": -0.2356, "timestamp": "1676156574.05"}, {"acc_x": 0.03, "acc_y": 0.98, "acc_z": 0.1067, "gy_x": 0.3142, "gy_y": -0.0113, "gy_z": -0.2711, "timestamp": "1676156574.0625"}, {"acc_x": 0.0235, "acc_y": 0.9995, "acc_z": 0.1, "gy_x": 1.0002, "gy_y": -0.344, "gy_z": -0.4483, "timestamp": "1676156574.075"}, {"acc_x": 0.02, "acc_y": 1.0056, "acc_z": 0.0956, "gy_x": 0.4326, "gy_y": -0.5549, "gy_z": -0.4856, "timestamp": "1676156574.0875"}, {"acc_x": 0.02, "acc_y": 0.9992, "acc_z": 0.0892, "gy_x": -0.135, "gy_y": -0.7658, "gy_z": -0.5228, "timestamp": "1676156574.1"}, {"acc_x": 0.02, "acc_y": 0.9929, "acc_z": 0.0829, "gy_x": -0.24, "gy_y": -0.8964, "gy_z": -0.5298, "timestamp": "1676156574.1125"}, {"acc_x": 0.0269, "acc_y": 0.9969, "acc_z": 0.08, "gy_x": 0.4408, "gy_y": -0.7083, "gy_z": -0.49, "timestamp": "1676156574.125"}, {"acc_x": 0.03, "acc_y": 0.9914, "acc_z": 0.0972, "gy_x": 0.8141, "gy_y": -0.5834, "gy_z": -0.4634, "timestamp": "1676156574.1375"}, {"acc_x": 0.04, "acc_y": 0.98, "acc_z": 0.1248, "gy_x": 1.102, "gy_y": -0.55, "gy_z": -0.548, "timestamp": "1676156574.15"}, {"acc_x": 0.04, "acc_y": 0.98, "acc_z": 0.1364, "gy_x": 0.604, "gy_y": -0.5809, "gy_z": -0.3597, "timestamp": "1676156574.1625"}, {"acc_x": 0.04, "acc_y": 0.98, "acc_z": 0.143, "gy_x": 0.7937, "gy_y": -0.4183, "gy_z": -0.4139, "timestamp": "1676156574.175"}, {"acc_x": 0.04, "acc_y": 0.98, "acc_z": 0.1492, "gy_x": 0.85, "gy_y": -0.4633, "gy_z": -0.3367, "timestamp": "1676156574.1875"}, {"acc_x": 0.03, "acc_y": 0.98, "acc_z": 0.15, "gy_x": 1.0093, "gy_y": -0.4069, "gy_z": -0.3626, "timestamp": "1676156574.2"}, {"acc_x": 0.029, "acc_y": 0.98, "acc_z": 0.15, "gy_x": 0.5958, "gy_y": -0.73, "gy_z": -0.4265, "timestamp": "1676156574.2125"}, {"acc_x": 0.0219, "acc_y": 0.98, "acc_z": 0.15, "gy_x": 0.4898, "gy_y": -0.73, "gy_z": -0.4, "timestamp": "1676156574.225"}, {"acc_x": 0.02, "acc_y": 0.9722, "acc_z": 0.15, "gy_x": 0.3838, "gy_y": -0.73, "gy_z": -0.3735, "timestamp": "1676156574.2375"}, {"acc_x": 0.01, "acc_y": 0.9748, "acc_z": 0.15, "gy_x": 0.2673, "gy_y": -0.6109, "gy_z": -0.31, "timestamp": "1676156574.25"}, {"acc_x": 0.0067, "acc_y": 0.97, "acc_z": 0.1533, "gy_x": 0.2072, "gy_y": -0.5276, "gy_z": -0.31, "timestamp": "1676156574.2625"}, {"acc_x": 0.01, "acc_y": 0.98, "acc_z": 0.15, "gy_x": 0.3264, "gy_y": -0.6438, "gy_z": -0.4384, "timestamp": "1676156574.275"}, {"acc_x": 0.01, "acc_y": 0.98, "acc_z": 0.15, "gy_x": 0.1855, "gy_y": -0.7528, "gy_z": -0.4657, "timestamp": "1676156574.2875"}, {"acc_x": 0.01, "acc_y": 0.98, "acc_z": 0.14, "gy_x": 0.3268, "gy_y": -0.6336, "gy_z": -0.49, "timestamp": "1676156574.3"}, {"acc_x": 0.01, "acc_y": 0.98, "acc_z": 0.1335, "gy_x": 6.2274, "gy_y": -0.85, "gy_z": -0.5254, "timestamp": "1676156574.3125"}, {"acc_x": 0.0159, "acc_y": 0.98, "acc_z": 0.1241, "gy_x": 13.5256, "gy_y": -0.85, "gy_z": -0.4974, "timestamp": "1676156574.325"}, {"acc_x": 0.04, "acc_y": 0.9839, "acc_z": 0.12, "gy_x": 0.7913, "gy_y": -0.7828, "gy_z": -0.5247, "timestamp": "1676156574.3375"}, {"acc_x": 0.04, "acc_y": 0.9889, "acc_z": 0.12, "gy_x": 0.5183, "gy_y": -0.8946, "gy_z": -0.471, "timestamp": "1676156574.35"}, {"acc_x": 0.0289, "acc_y": 0.9811, "acc_z": 0.1111, "gy_x": 0.172, "gy_y": -1.158, "gy_z": -0.548, "timestamp": "1676156574.3625"}, {"acc_x": 0.022, "acc_y": 0.988, "acc_z": 0.118, "gy_x": 0.0646, "gy_y": -1.1312, "gy_z": -0.5212, "timestamp": "1676156574.375"}, {"acc_x": 0.02, "acc_y": 0.9818, "acc_z": 0.12, "gy_x": -0.0428, "gy_y": -1.1043, "gy_z": -0.4943, "timestamp": "1676156574.3875"}, {"acc_x": 0.02, "acc_y": 0.98, "acc_z": 0.13, "gy_x": 0.3803, "gy_y": -1.0335, "gy_z": -0.4279, "timestamp": "1676156574.4"}, {"acc_x": 0.02, "acc_y": 0.98, "acc_z": 0.133, "gy_x": 0.564, "gy_y": -0.9171, "gy_z": -0.3912, "timestamp": "1676156574.4125"}, {"acc_x": 0.0224, "acc_y": 0.98, "acc_z": 0.14, "gy_x": 0.7157, "gy_y": -0.7527, "gy_z": -0.37, "timestamp": "1676156574.425"}, {"acc_x": 0.0293, "acc_y": 0.98, "acc_z": 0.14, "gy_x": 0.6613, "gy_y": -0.8388, "gy_z": -0.37, "timestamp": "1676156574.4375"}, {"acc_x": 0.02, "acc_y": 0.98, "acc_z": 0.14, "gy_x": 0.2558, "gy_y": -0.8694, "gy_z": -0.4567, "timestamp": "1676156574.45"}, {"acc_x": 0.0133, "acc_y": 0.98, "acc_z": 0.1467, "gy_x": 0.4884, "gy_y": -0.6827, "gy_z": -0.5027, "timestamp": "1676156574.4625"}, {"acc_x": 0.01, "acc_y": 0.98, "acc_z": 0.15, "gy_x": 0.6201, "gy_y": -0.6299, "gy_z": -0.4499, "timestamp": "1676156574.475"}, {"acc_x": 0.02, "acc_y": 0.98, "acc_z": 0.1464, "gy_x": 0.7015, "gy_y": -0.5626, "gy_z": -0.3353, "timestamp": "1676156574.4875"}, {"acc_x": 0.02, "acc_y": 0.98, "acc_z": 0.14, "gy_x": 0.51, "gy_y": -0.59, "gy_z": -0.39, "timestamp": "1676156574.5"}, {"acc_x": 0.03, "acc_y": 0.98, "acc_z": 0.14, "gy_x": 0.3301, "gy_y": -0.399, "gy_z": -0.3041, "timestamp": "1676156574.5125"}, {"acc_x": 0.03, "acc_y": 0.98, "acc_z": 0.14, "gy_x": 0.4358, "gy_y": -0.236, "gy_z": -0.2733, "timestamp": "1676156574.525"}, {"acc_x": 0.03, "acc_y": 0.98, "acc_z": 0.14, "gy_x": 0.5416, "gy_y": -0.073, "gy_z": -0.2425, "timestamp": "1676156574.5375"}, {"acc_x": 0.03, "acc_y": 0.98, "acc_z": 0.13, "gy_x": 0.31, "gy_y": 0.0, "gy_z": -0.2194, "timestamp": "1676156574.55"}, {"acc_x": 0.027, "acc_y": 0.98, "acc_z": 0.13, "gy_x": 0.31, "gy_y": 0.0, "gy_z": -0.1929, "timestamp": "1676156574.5625"}, {"acc_x": 0.02, "acc_y": 0.98, "acc_z": 0.1276, "gy_x": 0.6023, "gy_y": -0.1442, "gy_z": -0.3534, "timestamp": "1676156574.575"}, {"acc_x": 0.02, "acc_y": 0.98, "acc_z": 0.1207, "gy_x": 0.5748, "gy_y": -0.2314, "gy_z": -0.2938, "timestamp": "1676156574.5875"}, {"acc_x": 0.02, "acc_y": 0.98, "acc_z": 0.12, "gy_x": 0.5428, "gy_y": -0.2871, "gy_z": -0.24, "timestamp": "1676156574.6"}, {"acc_x": 0.03, "acc_y": 0.98, "acc_z": 0.13, "gy_x": 0.5487, "gy_y": -0.0711, "gy_z": -0.24, "timestamp": "1676156574.6125"}, {"acc_x": 0.03, "acc_y": 0.98, "acc_z": 0.13, "gy_x": 0.7606, "gy_y": 0.1055, "gy_z": -0.24, "timestamp": "1676156574.625"}, {"acc_x": 0.0161, "acc_y": 0.98, "acc_z": 0.1339, "gy_x": 0.471, "gy_y": 0.0294, "gy_z": -0.1237, "timestamp": "1676156574.6375"}, {"acc_x": 0.01, "acc_y": 0.98, "acc_z": 0.14, "gy_x": 0.3343, "gy_y": -0.0235, "gy_z": -0.234, "timestamp": "1676156574.65"}, {"acc_x": 0.02, "acc_y": 0.98, "acc_z": 0.14, "gy_x": 0.7819, "gy_y": -0.1241, "gy_z": -0.3141, "timestamp": "1676156574.6625"}, {"acc_x": 0.02, "acc_y": 0.98, "acc_z": 0.14, "gy_x": 0.6705, "gy_y": -0.1798, "gy_z": -0.3698, "timestamp": "1676156574.675"}, {"acc_x": 0.02, "acc_y": 0.98, "acc_z": 0.14, "gy_x": 0.5591, "gy_y": -0.2355, "gy_z": -0.4255, "timestamp": "1676156574.6875"}, {"acc_x": 0.02, "acc_y": 0.98, "acc_z": 0.14, "gy_x": 0.43, "gy_y": -0.5832, "gy_z": -0.3286, "timestamp": "1676156574.7"}, {"acc_x": 0.0165, "acc_y": 0.98, "acc_z": 0.1365, "gy_x": 0.43, "gy_y": -0.7204, "gy_z": -0.3561, "timestamp": "1676156574.7125"}, {"acc_x": 0.0123, "acc_y": 0.98, "acc_z": 0.14, "gy_x": 0.4007, "gy_y": -0.8918, "gy_z": -0.5143, "timestamp": "1676156574.725"}, {"acc_x": 0.0191, "acc_y": 0.98, "acc_z": 0.14, "gy_x": 0.6732, "gy_y": -0.8069, "gy_z": -0.4071, "timestamp": "1676156574.7375"}, {"acc_x": 0.04, "acc_y": 0.98, "acc_z": 0.1399, "gy_x": 0.3629, "gy_y": -0.7086, "gy_z": -0.5357, "timestamp": "1676156574.75"}, {"acc_x": 0.04, "acc_y": 0.98, "acc_z": 0.1332, "gy_x": 0.31, "gy_y": -0.5013, "gy_z": -0.4787, "timestamp": "1676156574.7625"}, {"acc_x": 0.0343, "acc_y": 0.98, "acc_z": 0.13, "gy_x": 0.31, "gy_y": -0.4468, "gy_z": -0.5332, "timestamp": "1676156574.775"}, {"acc_x": 0.02, "acc_y": 0.98, "acc_z": 0.13, "gy_x": 0.4157, "gy_y": -0.5813, "gy_z": -0.2711, "timestamp": "1676156574.7875"}, {"acc_x": 0.02, "acc_y": 0.98, "acc_z": 0.13, "gy_x": 0.3886, "gy_y": -0.5273, "gy_z": -0.3296, "timestamp": "1676156574.8"}, {"acc_x": 0.02, "acc_y": 0.98, "acc_z": 0.13, "gy_x": 0.49, "gy_y": -0.4701, "gy_z": -0.4499, "timestamp": "1676156574.8125"}, {"acc_x": 0.02, "acc_y": 0.98, "acc_z": 0.13, "gy_x": 0.5094, "gy_y": -0.5889, "gy_z": -0.37, "timestamp": "1676156574.825"}, {"acc_x": 0.0117, "acc_y": 0.98, "acc_z": 0.13, "gy_x": 0.5451, "gy_y": -0.6602, "gy_z": -0.37, "timestamp": "1676156574.8375"}, {"acc_x": 0.01, "acc_y": 0.98, "acc_z": 0.14, "gy_x": 0.4346, "gy_y": -0.9085, "gy_z": -0.6285, "timestamp": "1676156574.85"}, {"acc_x": 0.0139, "acc_y": 0.98, "acc_z": 0.14, "gy_x": 0.3558, "gy_y": -0.9917, "gy_z": -0.6547, "timestamp": "1676156574.8625"}, {"acc_x": 0.0215, "acc_y": 0.98, "acc_z": 0.14, "gy_x": 0.557, "gy_y": -1.093, "gy_z": -0.61, "timestamp": "1676156574.875"}, {"acc_x": 0.0261, "acc_y": 0.98, "acc_z": 0.14, "gy_x": 0.5842, "gy_y": -1.0658, "gy_z": -0.61, "timestamp": "1676156574.8875"}, {"acc_x": 0.03, "acc_y": 0.98, "acc_z": 0.14, "gy_x": 0.4947, "gy_y": -1.04, "gy_z": -0.5331, "timestamp": "1676156574.9"}, {"acc_x": 0.0237, "acc_y": 0.98, "acc_z": 0.14, "gy_x": 0.4045, "gy_y": -0.9337, "gy_z": -0.439, "timestamp": "1676156574.9125"}, {"acc_x": 0.02, "acc_y": 0.98, "acc_z": 0.14, "gy_x": 0.3782, "gy_y": -0.8243, "gy_z": -0.3864, "timestamp": "1676156574.925"}, {"acc_x": 0.02, "acc_y": 0.98, "acc_z": 0.1363, "gy_x": 0.5475, "gy_y": -1.015, "gy_z": -0.515, "timestamp": "1676156574.9375"}, {"acc_x": 0.0211, "acc_y": 0.98, "acc_z": 0.13, "gy_x": 0.4077, "gy_y": -0.9591, "gy_z": -0.5709, "timestamp": "1676156574.95"}, {"acc_x": 0.019, "acc_y": 0.98, "acc_z": 0.13, "gy_x": 0.6083, "gy_y": -0.918, "gy_z": -0.6683, "timestamp": "1676156574.9625"}, {"acc_x": 0.0122, "acc_y": 0.98, "acc_z": 0.13, "gy_x": 0.5805, "gy_y": -0.8855, "gy_z": -0.6405, "timestamp": "1676156574.975"}, {"acc_x": 0.01, "acc_y": 0.98, "acc_z": 0.13, "gy_x": 0.5526, "gy_y": -0.853, "gy_z": -0.6126, "timestamp": "1676156574.9875"}, {"acc_x": 0.01, "acc_y": 0.98, "acc_z": 0.13, "gy_x": 0.4066, "gy_y": -1.0817, "gy_z": -0.4717, "timestamp": "1676156575.0"}, {"acc_x": 0.0132, "acc_y": 0.98, "acc_z": 0.13, "gy_x": 0.4616, "gy_y": -1.0542, "gy_z": -0.4442, "timestamp": "1676156575.0125"}, {"acc_x": 0.03, "acc_y": 0.98, "acc_z": 0.14, "gy_x": 0.5325, "gy_y": -1.2712, "gy_z": -0.4812, "timestamp": "1676156575.025"}, {"acc_x": 0.03, "acc_y": 0.98, "acc_z": 0.14, "gy_x": 0.4783, "gy_y": -1.2442, "gy_z": -0.4542, "timestamp": "1676156575.0375"}, {"acc_x": 0.04, "acc_y": 0.98, "acc_z": 0.14, "gy_x": 0.3705, "gy_y": -0.9779, "gy_z": -0.5399, "timestamp": "1676156575.05"}, {"acc_x": 0.0465, "acc_y": 0.98, "acc_z": 0.14, "gy_x": 0.5724, "gy_y": -0.67, "gy_z": -0.4656, "timestamp": "1676156575.0625"}, {"acc_x": 0.05, "acc_y": 0.98, "acc_z": 0.14, "gy_x": 0.4599, "gy_y": -0.67, "gy_z": -0.4375, "timestamp": "1676156575.075"}, {"acc_x": 0.0461, "acc_y": 0.98, "acc_z": 0.1361, "gy_x": 0.37, "gy_y": -0.1858, "gy_z": -0.4029, "timestamp": "1676156575.0875"}, {"acc_x": 0.0374, "acc_y": 0.98, "acc_z": 0.1313, "gy_x": 0.37, "gy_y": -0.0782, "gy_z": -0.3491, "timestamp": "1676156575.1"}, {"acc_x": 0.0187, "acc_y": 0.98, "acc_z": 0.13, "gy_x": 0.1289, "gy_y": -0.3535, "gy_z": -0.37, "timestamp": "1676156575.1125"}, {"acc_x": 0.0122, "acc_y": 0.98, "acc_z": 0.13, "gy_x": 0.3831, "gy_y": -0.2887, "gy_z": -0.3883, "timestamp": "1676156575.125"}, {"acc_x": 0.01, "acc_y": 0.98, "acc_z": 0.13, "gy_x": 0.5319, "gy_y": -0.2453, "gy_z": -0.4255, "timestamp": "1676156575.1375"}, {"acc_x": 0.0152, "acc_y": 0.98, "acc_z": 0.13, "gy_x": 0.2794, "gy_y": -0.55, "gy_z": -0.3892, "timestamp": "1676156575.15"}, {"acc_x": 0.02, "acc_y": 0.98, "acc_z": 0.13, "gy_x": 0.4174, "gy_y": -0.55, "gy_z": -0.4159, "timestamp": "1676156575.1625"}, {"acc_x": 0.03, "acc_y": 0.98, "acc_z": 0.13, "gy_x": 0.3518, "gy_y": -0.31, "gy_z": -0.4551, "timestamp": "1676156575.175"}, {"acc_x": 0.03, "acc_y": 0.98, "acc_z": 0.13, "gy_x": 0.485, "gy_y": -0.31, "gy_z": -0.3441, "timestamp": "1676156575.1875"}, {"acc_x": 0.03, "acc_y": 0.98, "acc_z": 0.13, "gy_x": 0.1907, "gy_y": 11.7428, "gy_z": -0.2934, "timestamp": "1676156575.2"}, {"acc_x": 0.0236, "acc_y": 0.98, "acc_z": 0.13, "gy_x": 0.4552, "gy_y": -0.0111, "gy_z": -0.2037, "timestamp": "1676156575.2125"}, {"acc_x": 0.02, "acc_y": 0.98, "acc_z": 0.1356, "gy_x": 0.35, "gy_y": -0.09, "gy_z": -0.23, "timestamp": "1676156575.225"}, {"acc_x": 0.02, "acc_y": 0.98, "acc_z": 0.14, "gy_x": 0.5414, "gy_y": -0.0857, "gy_z": -0.3229, "timestamp": "1676156575.2375"}, {"acc_x": 0.02, "acc_y": 0.98, "acc_z": 0.14, "gy_x": 0.6532, "gy_y": -0.1416, "gy_z": -0.3508, "timestamp": "1676156575.25"}, {"acc_x": 0.029, "acc_y": 0.98, "acc_z": 0.139, "gy_x": 0.467, "gy_y": -0.6506, "gy_z": -0.37, "timestamp": "1676156575.2625"}, {"acc_x": 0.0221, "acc_y": 0.98, "acc_z": 0.1321, "gy_x": 0.6136, "gy_y": -0.61, "gy_z": -0.3293, "timestamp": "1676156575.275"}, {"acc_x": 0.02, "acc_y": 0.98, "acc_z": 0.13, "gy_x": 0.5041, "gy_y": -0.61, "gy_z": -0.2502, "timestamp": "1676156575.2875"}, {"acc_x": 0.02, "acc_y": 0.98, "acc_z": 0.13, "gy_x": 0.4103, "gy_y": -0.3494, "gy_z": -0.24, "timestamp": "1676156575.3"}, {"acc_x": 0.02, "acc_y": 0.98, "acc_z": 0.13, "gy_x": 0.3826, "gy_y": -0.4047, "gy_z": -0.24, "timestamp": "1676156575.3125"}, {"acc_x": 0.02, "acc_y": 0.9875, "acc_z": 0.13, "gy_x": 0.8598, "gy_y": -0.2666, "gy_z": -0.4036, "timestamp": "1676156575.325"}, {"acc_x": 0.02, "acc_y": 0.981, "acc_z": 0.13, "gy_x": 0.6619, "gy_y": -0.3541, "gy_z": -0.5141, "timestamp": "1676156575.3375"}, {"acc_x": 0.02, "acc_y": 0.98, "acc_z": 0.13, "gy_x": 0.5394, "gy_y": -0.6771, "gy_z": -0.5112, "timestamp": "1676156575.35"}, {"acc_x": 0.02, "acc_y": 0.98, "acc_z": 0.13, "gy_x": 0.6918, "gy_y": -0.7546, "gy_z": -0.3946, "timestamp": "1676156575.3625"}, {"acc_x": 0.02, "acc_y": 0.98, "acc_z": 0.13, "gy_x": 0.5817, "gy_y": -0.7821, "gy_z": -0.4221, "timestamp": "1676156575.375"}, {"acc_x": 0.02, "acc_y": 0.98, "acc_z": 0.13, "gy_x": 0.8524, "gy_y": -0.7774, "gy_z": -0.4551, "timestamp": "1676156575.3875"}, {"acc_x": 0.0212, "acc_y": 0.98, "acc_z": 0.13, "gy_x": 0.5825, "gy_y": -0.7509, "gy_z": -0.5082, "timestamp": "1676156575.4"}, {"acc_x": 0.03, "acc_y": 0.98, "acc_z": 0.1306, "gy_x": 0.4386, "gy_y": -0.7345, "gy_z": -0.4286, "timestamp": "1676156575.4125"}, {"acc_x": 0.03, "acc_y": 0.98, "acc_z": 0.135, "gy_x": 0.5971, "gy_y": -0.8182, "gy_z": -0.4022, "timestamp": "1676156575.425"}, {"acc_x": 0.03, "acc_y": 0.98, "acc_z": 0.1394, "gy_x": 0.7556, "gy_y": -0.9018, "gy_z": -0.3757, "timestamp": "1676156575.4375"}, {"acc_x": 0.0247, "acc_y": 0.98, "acc_z": 0.14, "gy_x": 0.5857, "gy_y": -0.67, "gy_z": -0.37, "timestamp": "1676156575.45"}, {"acc_x": 0.02, "acc_y": 0.98, "acc_z": 0.1437, "gy_x": 0.478, "gy_y": -0.67, "gy_z": -0.37, "timestamp": "1676156575.4625"}, {"acc_x": 0.02, "acc_y": 0.98, "acc_z": 0.15, "gy_x": 0.4382, "gy_y": -0.7135, "gy_z": -0.3182, "timestamp": "1676156575.475"}, {"acc_x": 0.02, "acc_y": 0.98, "acc_z": 0.15, "gy_x": 0.4648, "gy_y": -0.6603, "gy_z": -0.3448, "timestamp": "1676156575.4875"}, {"acc_x": 0.03, "acc_y": 0.98, "acc_z": 0.15, "gy_x": 0.4105, "gy_y": -0.5702, "gy_z": -0.4495, "timestamp": "1676156575.5"}, {"acc_x": 0.0234, "acc_y": 0.98, "acc_z": 0.1434, "gy_x": 0.2662, "gy_y": -0.4798, "gy_z": -0.4198, "timestamp": "1676156575.5125"}, {"acc_x": 0.02, "acc_y": 0.98, "acc_z": 0.1341, "gy_x": 0.1501, "gy_y": -0.5355, "gy_z": -0.4755, "timestamp": "1676156575.525"}, {"acc_x": 0.02, "acc_y": 0.9875, "acc_z": 0.13, "gy_x": 0.2553, "gy_y": -0.5031, "gy_z": -0.3494, "timestamp": "1676156575.5375"}, {"acc_x": 0.02, "acc_y": 0.9833, "acc_z": 0.13, "gy_x": 0.2859, "gy_y": -0.5294, "gy_z": -0.4281, "timestamp": "1676156575.55"}, {"acc_x": 0.0209, "acc_y": 0.98, "acc_z": 0.13, "gy_x": 0.43, "gy_y": -0.5992, "gy_z": -0.4828, "timestamp": "1676156575.5625"}, {"acc_x": 0.0278, "acc_y": 0.98, "acc_z": 0.13, "gy_x": 0.43, "gy_y": -0.5188, "gy_z": -0.4292, "timestamp": "1676156575.575"}, {"acc_x": 0.03, "acc_y": 0.98, "acc_z": 0.13, "gy_x": 0.43, "gy_y": -0.4385, "gy_z": -0.3757, "timestamp": "1676156575.5875"}, {"acc_x": 0.02, "acc_y": 0.98, "acc_z": 0.1349, "gy_x": 0.3005, "gy_y": -0.31, "gy_z": -0.3677, "timestamp": "1676156575.6"}, {"acc_x": 0.02, "acc_y": 0.98, "acc_z": 0.14, "gy_x": 0.1394, "gy_y": -0.31, "gy_z": -0.329, "timestamp": "1676156575.6125"}, {"acc_x": 0.02, "acc_y": 0.98, "acc_z": 0.14, "gy_x": 0.4157, "gy_y": -0.5957, "gy_z": -0.5213, "timestamp": "1676156575.625"}, {"acc_x": 0.02, "acc_y": 0.98, "acc_z": 0.14, "gy_x": 0.3621, "gy_y": -0.5421, "gy_z": -0.4141, "timestamp": "1676156575.6375"}, {"acc_x": 0.02, "acc_y": 0.98, "acc_z": 0.1364, "gy_x": 0.2848, "gy_y": -0.4684, "gy_z": -0.3316, "timestamp": "1676156575.65"}, {"acc_x": 0.0133, "acc_y": 0.98, "acc_z": 0.1367, "gy_x": 0.1905, "gy_y": -0.4795, "gy_z": -0.469, "timestamp": "1676156575.6625"}, {"acc_x": 0.01, "acc_y": 0.98, "acc_z": 0.14, "gy_x": 0.1384, "gy_y": -0.5316, "gy_z": -0.5733, "timestamp": "1676156575.675"}, {"acc_x": 0.0136, "acc_y": 0.98, "acc_z": 0.14, "gy_x": 0.337, "gy_y": -0.6852, "gy_z": -0.5205, "timestamp": "1676156575.6875"}, {"acc_x": 0.02, "acc_y": 0.98, "acc_z": 0.14, "gy_x": 0.2789, "gy_y": -0.7121, "gy_z": -0.5741, "timestamp": "1676156575.7"}, {"acc_x": 0.02, "acc_y": 0.98, "acc_z": 0.14, "gy_x": 0.6544, "gy_y": -0.6834, "gy_z": -0.7822, "timestamp": "1676156575.7125"}, {"acc_x": 0.02, "acc_y": 0.98, "acc_z": 0.14, "gy_x": 0.4896, "gy_y": -0.8253, "gy_z": -0.6998, "timestamp": "1676156575.725"}, {"acc_x": 0.0281, "acc_y": 0.98, "acc_z": 0.14, "gy_x": 0.3248, "gy_y": -0.9673, "gy_z": -0.6174, "timestamp": "1676156575.7375"}, {"acc_x": 0.03, "acc_y": 0.98, "acc_z": 0.145, "gy_x": 0.2338, "gy_y": -0.9383, "gy_z": -0.5683, "timestamp": "1676156575.75"}, {"acc_x": 0.03, "acc_y": 0.9767, "acc_z": 0.15, "gy_x": 0.1188, "gy_y": -0.9659, "gy_z": -0.5959, "timestamp": "1676156575.7625"}, {"acc_x": 0.0173, "acc_y": 0.98, "acc_z": 0.1527, "gy_x": 0.3135, "gy_y": -0.5225, "gy_z": -0.55, "timestamp": "1676156575.775"}, {"acc_x": 0.0107, "acc_y": 0.98, "acc_z": 0.1593, "gy_x": 0.1416, "gy_y": -0.4389, "gy_z": -0.55, "timestamp": "1676156575.7875"}, {"acc_x": 0.01, "acc_y": 0.9799, "acc_z": 0.1601, "gy_x": 0.1814, "gy_y": 0.1885, "gy_z": -0.367, "timestamp": "1676156575.8"}, {"acc_x": 0.01, "acc_y": 0.9733, "acc_z": 0.1667, "gy_x": 0.1951, "gy_y": 0.6192, "gy_z": -0.2288, "timestamp": "1676156575.8125"}, {"acc_x": 0.01, "acc_y": 0.97, "acc_z": 0.1637, "gy_x": 0.0448, "gy_y": 0.851, "gy_z": -0.1912, "timestamp": "1676156575.825"}, {"acc_x": 0.01, "acc_y": 0.98, "acc_z": 0.1636, "gy_x": 0.574, "gy_y": 2.1528, "gy_z": -0.2272, "timestamp": "1676156575.8375"}, {"acc_x": 0.01, "acc_y": 0.9805, "acc_z": 0.1695, "gy_x": 0.2374, "gy_y": 2.1805, "gy_z": -0.1995, "timestamp": "1676156575.85"}, {"acc_x": 0.013, "acc_y": 0.984, "acc_z": 0.157, "gy_x": -0.3406, "gy_y": 2.4839, "gy_z": -0.0116, "timestamp": "1676156575.8625"}, {"acc_x": 0.0326, "acc_y": 0.97, "acc_z": 0.1563, "gy_x": 1.285, "gy_y": 3.368, "gy_z": 0.12, "timestamp": "1676156575.875"}, {"acc_x": 0.0321, "acc_y": 0.9779, "acc_z": 0.16, "gy_x": 1.0094, "gy_y": 3.2433, "gy_z": 0.12, "timestamp": "1676156575.8875"}, {"acc_x": 0.04, "acc_y": 0.98, "acc_z": 0.175, "gy_x": 0.1399, "gy_y": 3.3965, "gy_z": 0.24, "timestamp": "1676156575.9"}, {"acc_x": 0.0417, "acc_y": 0.9783, "acc_z": 0.18, "gy_x": 0.0852, "gy_y": 3.2825, "gy_z": 0.24, "timestamp": "1676156575.9125"}, {"acc_x": 0.0481, "acc_y": 0.9719, "acc_z": 0.18, "gy_x": 1.1488, "gy_y": 3.706, "gy_z": 0.1329, "timestamp": "1676156575.925"}, {"acc_x": 0.042, "acc_y": 0.97, "acc_z": 0.178, "gy_x": 0.3259, "gy_y": 3.36, "gy_z": 0.098, "timestamp": "1676156575.9375"}, {"acc_x": 0.03, "acc_y": 0.9642, "acc_z": 0.1842, "gy_x": 0.3021, "gy_y": 3.3687, "gy_z": 0.1295, "timestamp": "1676156575.95"}, {"acc_x": 0.0237, "acc_y": 0.9727, "acc_z": 0.1863, "gy_x": 0.1788, "gy_y": 3.3446, "gy_z": 0.18, "timestamp": "1676156575.9625"}, {"acc_x": 0.0256, "acc_y": 0.9744, "acc_z": 0.1844, "gy_x": -0.4533, "gy_y": 3.0806, "gy_z": 0.18, "timestamp": "1676156575.975"}, {"acc_x": 0.0249, "acc_y": 0.9825, "acc_z": 0.1825, "gy_x": 0.3357, "gy_y": 3.3803, "gy_z": 0.1079, "timestamp": "1676156575.9875"}]