[{"acc_x": 0.0487, "acc_y": 0.9725, "acc_z": 0.0825, "gy_x": 2.3495, "gy_y": 1.1494, "gy_z": -0.3893, "timestamp": "1676156091.0875"}, {"acc_x": 0.0411, "acc_y": 0.9811, "acc_z": 0.0889, "gy_x": 1.8615, "gy_y": 0.8847, "gy_z": -0.3975, "timestamp": "1676156091.1"}, {"acc_x": 0.05, "acc_y": 0.99, "acc_z": 0.083, "gy_x": -0.1204, "gy_y": 0.1012, "gy_z": -0.12, "timestamp": "1676156091.1125"}, {"acc_x": 0.0438, "acc_y": 0.9962, "acc_z": 0.0838, "gy_x": 1.0052, "gy_y": 0.2849, "gy_z": -0.1721, "timestamp": "1676156091.125"}, {"acc_x": 0.0244, "acc_y": 0.9922, "acc_z": 0.0722, "gy_x": 0.2096, "gy_y": 0.0828, "gy_z": -0.296, "timestamp": "1676156091.1375"}, {"acc_x": 0.0194, "acc_y": 0.9989, "acc_z": 0.07, "gy_x": 0.1509, "gy_y": -0.2385, "gy_z": -0.31, "timestamp": "1676156091.15"}, {"acc_x": 0.0137, "acc_y": 0.9837, "acc_z": 0.0737, "gy_x": 0.8971, "gy_y": -0.2018, "gy_z": -0.31, "timestamp": "1676156091.1625"}, {"acc_x": 0.02, "acc_y": 0.99, "acc_z": 0.08, "gy_x": 0.3975, "gy_y": -0.2723, "gy_z": -0.37, "timestamp": "1676156091.175"}, {"acc_x": 0.0282, "acc_y": 0.99, "acc_z": 0.0882, "gy_x": 0.5949, "gy_y": -0.1332, "gy_z": -0.4168, "timestamp": "1676156091.1875"}, {"acc_x": 0.03, "acc_y": 0.98, "acc_z": 0.1016, "gy_x": 0.806, "gy_y": -0.2367, "gy_z": -0.404, "timestamp": "1676156091.2"}, {"acc_x": 0.022, "acc_y": 0.984, "acc_z": 0.134, "gy_x": 0.8102, "gy_y": -0.5873, "gy_z": -0.37, "timestamp": "1676156091.2125"}, {"acc_x": 0.01, "acc_y": 0.9843, "acc_z": 0.1457, "gy_x": 0.8939, "gy_y": -0.7419, "gy_z": -0.37, "timestamp": "1676156091.225"}, {"acc_x": 0.0009, "acc_y": 0.9709, "acc_z": 0.1591, "gy_x": 0.98, "gy_y": -1.2892, "gy_z": -0.5246, "timestamp": "1676156091.2375"}, {"acc_x": 0.0015, "acc_y": 0.9785, "acc_z": 0.17, "gy_x": 0.6453, "gy_y": -1.5759, "gy_z": -0.5829, "timestamp": "1676156091.25"}, {"acc_x": 0.01, "acc_y": 0.97, "acc_z": 0.17, "gy_x": 0.6429, "gy_y": -1.8639, "gy_z": -0.567, "timestamp": "1676156091.2625"}, {"acc_x": 0.016, "acc_y": 0.97, "acc_z": 0.164, "gy_x": 0.1408, "gy_y": -1.8241, "gy_z": -0.628, "timestamp": "1676156091.275"}, {"acc_x": 0.02, "acc_y": 0.9783, "acc_z": 0.1517, "gy_x": 0.5809, "gy_y": -1.5482, "gy_z": -0.6674, "timestamp": "1676156091.2875"}, {"acc_x": 0.0211, "acc_y": 0.98, "acc_z": 0.14, "gy_x": 0.0604, "gy_y": -1.3395, "gy_z": -0.4902, "timestamp": "1676156091.3"}, {"acc_x": 0.03, "acc_y": 0.98, "acc_z": 0.1365, "gy_x": 0.2207, "gy_y": -1.1472, "gy_z": -0.5671, "timestamp": "1676156091.3125"}, {"acc_x": 0.0356, "acc_y": 0.98, "acc_z": 0.1244, "gy_x": 0.1186, "gy_y": -0.996, "gy_z": -0.579, "timestamp": "1676156091.325"}, {"acc_x": 0.0358, "acc_y": 0.9842, "acc_z": 0.1242, "gy_x": 0.4456, "gy_y": -0.7089, "gy_z": -0.6591, "timestamp": "1676156091.3375"}, {"acc_x": 0.03, "acc_y": 0.98, "acc_z": 0.12, "gy_x": -0.3668, "gy_y": -0.9197, "gy_z": -0.61, "timestamp": "1676156091.35"}, {"acc_x": 0.0162, "acc_y": 0.99, "acc_z": 0.12, "gy_x": 0.3553, "gy_y": -0.8972, "gy_z": -0.6009, "timestamp": "1676156091.3625"}, {"acc_x": 0.01, "acc_y": 0.9841, "acc_z": 0.12, "gy_x": 0.0475, "gy_y": -1.092, "gy_z": -0.5632, "timestamp": "1676156091.375"}, {"acc_x": 0.0182, "acc_y": 0.98, "acc_z": 0.1282, "gy_x": 0.55, "gy_y": -0.92, "gy_z": -0.625, "timestamp": "1676156091.3875"}, {"acc_x": 0.0145, "acc_y": 0.98, "acc_z": 0.13, "gy_x": 0.5672, "gy_y": -0.9234, "gy_z": -0.55, "timestamp": "1676156091.4"}, {"acc_x": 0.0179, "acc_y": 0.9821, "acc_z": 0.1321, "gy_x": 0.7856, "gy_y": -0.98, "gy_z": -0.5339, "timestamp": "1676156091.4125"}, {"acc_x": 0.0159, "acc_y": 0.9841, "acc_z": 0.14, "gy_x": 0.6741, "gy_y": -0.964, "gy_z": -0.5221, "timestamp": "1676156091.425"}, {"acc_x": 0.02, "acc_y": 0.98, "acc_z": 0.1323, "gy_x": 0.831, "gy_y": -0.9247, "gy_z": -0.6005, "timestamp": "1676156091.4375"}, {"acc_x": 0.0311, "acc_y": 0.97, "acc_z": 0.1411, "gy_x": 0.7831, "gy_y": -0.9182, "gy_z": -0.3688, "timestamp": "1676156091.45"}, {"acc_x": 0.046, "acc_y": 0.97, "acc_z": 0.156, "gy_x": 0.3035, "gy_y": -0.7934, "gy_z": -0.2834, "timestamp": "1676156091.4625"}, {"acc_x": 0.06, "acc_y": 0.97, "acc_z": 0.1645, "gy_x": 0.9045, "gy_y": 0.2999, "gy_z": -0.12, "timestamp": "1676156091.475"}, {"acc_x": 0.0518, "acc_y": 0.9782, "acc_z": 0.16, "gy_x": 0.5571, "gy_y": 0.4737, "gy_z": -0.1709, "timestamp": "1676156091.4875"}, {"acc_x": 0.0296, "acc_y": 0.98, "acc_z": 0.16, "gy_x": 0.1758, "gy_y": 0.4234, "gy_z": -0.1821, "timestamp": "1676156091.5"}, {"acc_x": 0.0166, "acc_y": 0.98, "acc_z": 0.1566, "gy_x": 0.0523, "gy_y": 0.2016, "gy_z": -0.2323, "timestamp": "1676156091.5125"}, {"acc_x": 0.004, "acc_y": 0.986, "acc_z": 0.144, "gy_x": 0.0127, "gy_y": 0.0036, "gy_z": -0.1927, "timestamp": "1676156091.525"}, {"acc_x": 0.0, "acc_y": 0.9806, "acc_z": 0.1211, "gy_x": 0.3276, "gy_y": -0.4199, "gy_z": -0.2517, "timestamp": "1676156091.5375"}, {"acc_x": -0.009, "acc_y": 0.98, "acc_z": 0.119, "gy_x": 0.3638, "gy_y": -0.43, "gy_z": -0.3448, "timestamp": "1676156091.55"}, {"acc_x": 0.0071, "acc_y": 0.9836, "acc_z": 0.1136, "gy_x": 0.165, "gy_y": -0.4981, "gy_z": -0.456, "timestamp": "1676156091.5625"}, {"acc_x": 0.0261, "acc_y": 0.99, "acc_z": 0.12, "gy_x": 0.6507, "gy_y": -0.5793, "gy_z": -0.4063, "timestamp": "1676156091.575"}, {"acc_x": 0.0386, "acc_y": 0.99, "acc_z": 0.12, "gy_x": 1.1077, "gy_y": -0.3915, "gy_z": -0.4814, "timestamp": "1676156091.5875"}, {"acc_x": 0.0494, "acc_y": 0.98, "acc_z": 0.1306, "gy_x": 0.4956, "gy_y": -0.3811, "gy_z": -0.3156, "timestamp": "1676156091.6"}, {"acc_x": 0.0369, "acc_y": 0.98, "acc_z": 0.14, "gy_x": 0.6074, "gy_y": -0.6048, "gy_z": -0.4274, "timestamp": "1676156091.6125"}, {"acc_x": 0.03, "acc_y": 0.98, "acc_z": 0.1339, "gy_x": 0.5208, "gy_y": -0.9147, "gy_z": -0.4303, "timestamp": "1676156091.625"}, {"acc_x": 0.0211, "acc_y": 0.98, "acc_z": 0.13, "gy_x": 0.4976, "gy_y": -0.9262, "gy_z": -0.4659, "timestamp": "1676156091.6375"}, {"acc_x": 0.0195, "acc_y": 0.98, "acc_z": 0.1305, "gy_x": 0.394, "gy_y": -1.04, "gy_z": -0.4896, "timestamp": "1676156091.65"}, {"acc_x": 0.01, "acc_y": 0.98, "acc_z": 0.14, "gy_x": 0.4013, "gy_y": -1.0843, "gy_z": -0.5343, "timestamp": "1676156091.6625"}, {"acc_x": 0.0159, "acc_y": 0.98, "acc_z": 0.14, "gy_x": 0.5573, "gy_y": -1.0063, "gy_z": -0.4563, "timestamp": "1676156091.675"}, {"acc_x": 0.02, "acc_y": 0.98, "acc_z": 0.1487, "gy_x": 0.5004, "gy_y": -0.6968, "gy_z": -0.5322, "timestamp": "1676156091.6875"}, {"acc_x": 0.03, "acc_y": 0.98, "acc_z": 0.149, "gy_x": 0.43, "gy_y": -0.5457, "gy_z": -0.4578, "timestamp": "1676156091.7"}, {"acc_x": 0.0264, "acc_y": 0.98, "acc_z": 0.14, "gy_x": 0.4145, "gy_y": -0.6523, "gy_z": -0.4145, "timestamp": "1676156091.7125"}, {"acc_x": 0.02, "acc_y": 0.98, "acc_z": 0.14, "gy_x": 0.272, "gy_y": -0.4141, "gy_z": -0.37, "timestamp": "1676156091.725"}, {"acc_x": 0.02, "acc_y": 0.98, "acc_z": 0.1315, "gy_x": 0.0292, "gy_y": -0.3747, "gy_z": -0.37, "timestamp": "1676156091.7375"}, {"acc_x": 0.02, "acc_y": 0.98, "acc_z": 0.1312, "gy_x": 0.5432, "gy_y": -0.373, "gy_z": -0.43, "timestamp": "1676156091.75"}, {"acc_x": 0.02, "acc_y": 0.98, "acc_z": 0.14, "gy_x": 0.1823, "gy_y": -0.5305, "gy_z": -0.43, "timestamp": "1676156091.7625"}, {"acc_x": 0.0263, "acc_y": 0.98, "acc_z": 0.14, "gy_x": 0.607, "gy_y": -0.67, "gy_z": -0.37, "timestamp": "1676156091.775"}, {"acc_x": 0.03, "acc_y": 0.98, "acc_z": 0.14, "gy_x": 0.5013, "gy_y": -0.67, "gy_z": -0.37, "timestamp": "1676156091.7875"}, {"acc_x": 0.03, "acc_y": 0.98, "acc_z": 0.13, "gy_x": 0.4301, "gy_y": -0.55, "gy_z": -0.43, "timestamp": "1676156091.8"}, {"acc_x": 0.0159, "acc_y": 0.98, "acc_z": 0.14, "gy_x": 0.4809, "gy_y": -0.55, "gy_z": -0.43, "timestamp": "1676156091.8125"}, {"acc_x": 0.0037, "acc_y": 0.98, "acc_z": 0.1463, "gy_x": 0.4445, "gy_y": -0.55, "gy_z": -0.43, "timestamp": "1676156091.825"}, {"acc_x": 0.0, "acc_y": 0.98, "acc_z": 0.1418, "gy_x": 0.4545, "gy_y": -0.8263, "gy_z": -0.3937, "timestamp": "1676156091.8375"}, {"acc_x": 0.0211, "acc_y": 0.98, "acc_z": 0.1411, "gy_x": 0.3947, "gy_y": -0.7547, "gy_z": -0.37, "timestamp": "1676156091.85"}, {"acc_x": 0.03, "acc_y": 0.98, "acc_z": 0.1469, "gy_x": 0.3431, "gy_y": -0.85, "gy_z": -0.4176, "timestamp": "1676156091.8625"}, {"acc_x": 0.0329, "acc_y": 0.98, "acc_z": 0.14, "gy_x": 0.2109, "gy_y": -0.7772, "gy_z": -0.3991, "timestamp": "1676156091.875"}, {"acc_x": 0.0393, "acc_y": 0.98, "acc_z": 0.14, "gy_x": 0.1347, "gy_y": -0.5867, "gy_z": -0.4753, "timestamp": "1676156091.8875"}, {"acc_x": 0.0292, "acc_y": 0.98, "acc_z": 0.14, "gy_x": 0.2426, "gy_y": -0.43, "gy_z": -0.3678, "timestamp": "1676156091.9"}, {"acc_x": 0.02, "acc_y": 0.98, "acc_z": 0.1363, "gy_x": 0.2872, "gy_y": -0.43, "gy_z": -0.3295, "timestamp": "1676156091.9125"}, {"acc_x": 0.02, "acc_y": 0.98, "acc_z": 0.1363, "gy_x": 0.3948, "gy_y": -0.37, "gy_z": -0.277, "timestamp": "1676156091.925"}, {"acc_x": 0.02, "acc_y": 0.98, "acc_z": 0.14, "gy_x": 0.4061, "gy_y": -0.37, "gy_z": -0.334, "timestamp": "1676156091.9375"}, {"acc_x": 0.0206, "acc_y": 0.98, "acc_z": 0.1394, "gy_x": 0.2068, "gy_y": -0.37, "gy_z": -0.3326, "timestamp": "1676156091.95"}, {"acc_x": 0.03, "acc_y": 0.98, "acc_z": 0.1316, "gy_x": 0.4882, "gy_y": -0.37, "gy_z": -0.31, "timestamp": "1676156091.9625"}, {"acc_x": 0.03, "acc_y": 0.98, "acc_z": 0.1382, "gy_x": 0.4408, "gy_y": -0.3346, "gy_z": -0.1979, "timestamp": "1676156091.975"}, {"acc_x": 0.0218, "acc_y": 0.98, "acc_z": 0.14, "gy_x": 0.24, "gy_y": -0.1199, "gy_z": -0.1656, "timestamp": "1676156091.9875"}, {"acc_x": 0.0189, "acc_y": 0.98, "acc_z": 0.14, "gy_x": 0.2098, "gy_y": 0.0004, "gy_z": -0.2756, "timestamp": "1676156092.0"}, {"acc_x": 0.01, "acc_y": 0.98, "acc_z": 0.1436, "gy_x": 0.6015, "gy_y": 0.0858, "gy_z": -0.24, "timestamp": "1676156092.0125"}, {"acc_x": 0.01, "acc_y": 0.98, "acc_z": 0.15, "gy_x": 0.4475, "gy_y": -0.0526, "gy_z": -0.278, "timestamp": "1676156092.025"}, {"acc_x": 0.01, "acc_y": 0.98, "acc_z": 0.15, "gy_x": 0.4848, "gy_y": -0.1644, "gy_z": -0.3587, "timestamp": "1676156092.0375"}, {"acc_x": 0.02, "acc_y": 0.98, "acc_z": 0.14, "gy_x": 0.31, "gy_y": -0.0647, "gy_z": -0.4889, "timestamp": "1676156092.05"}, {"acc_x": 0.023, "acc_y": 0.98, "acc_z": 0.14, "gy_x": 0.31, "gy_y": -0.2283, "gy_z": -0.4496, "timestamp": "1676156092.0625"}, {"acc_x": 0.03, "acc_y": 0.98, "acc_z": 0.14, "gy_x": 0.4349, "gy_y": -0.2024, "gy_z": -0.4073, "timestamp": "1676156092.075"}, {"acc_x": 0.0215, "acc_y": 0.98, "acc_z": 0.1315, "gy_x": 0.5381, "gy_y": 0.0363, "gy_z": -0.4178, "timestamp": "1676156092.0875"}, {"acc_x": 0.02, "acc_y": 0.98, "acc_z": 0.1305, "gy_x": 0.4918, "gy_y": -0.0269, "gy_z": -0.3396, "timestamp": "1676156092.1"}, {"acc_x": 0.02, "acc_y": 0.98, "acc_z": 0.14, "gy_x": 0.6925, "gy_y": 0.1321, "gy_z": -0.3604, "timestamp": "1676156092.1125"}, {"acc_x": 0.0258, "acc_y": 0.9742, "acc_z": 0.14, "gy_x": 0.2989, "gy_y": -0.0615, "gy_z": -0.3217, "timestamp": "1676156092.125"}, {"acc_x": 0.03, "acc_y": 0.9785, "acc_z": 0.14, "gy_x": 0.2988, "gy_y": -0.2689, "gy_z": -0.37, "timestamp": "1676156092.1375"}, {"acc_x": 0.03, "acc_y": 0.98, "acc_z": 0.1389, "gy_x": 0.4617, "gy_y": -0.37, "gy_z": -0.4319, "timestamp": "1676156092.15"}, {"acc_x": 0.03, "acc_y": 0.98, "acc_z": 0.133, "gy_x": 0.4302, "gy_y": -0.658, "gy_z": -0.2782, "timestamp": "1676156092.1625"}, {"acc_x": 0.0244, "acc_y": 0.98, "acc_z": 0.14, "gy_x": 0.5492, "gy_y": -0.6396, "gy_z": -0.4596, "timestamp": "1676156092.175"}, {"acc_x": 0.0277, "acc_y": 0.98, "acc_z": 0.14, "gy_x": 0.2182, "gy_y": -0.7206, "gy_z": -0.5406, "timestamp": "1676156092.1875"}, {"acc_x": 0.03, "acc_y": 0.98, "acc_z": 0.1387, "gy_x": 0.437, "gy_y": -0.611, "gy_z": -0.428, "timestamp": "1676156092.2"}, {"acc_x": 0.03, "acc_y": 0.98, "acc_z": 0.13, "gy_x": 0.7132, "gy_y": -0.6505, "gy_z": -0.3491, "timestamp": "1676156092.2125"}, {"acc_x": 0.0238, "acc_y": 0.98, "acc_z": 0.13, "gy_x": 0.1191, "gy_y": -0.6091, "gy_z": -0.3396, "timestamp": "1676156092.225"}, {"acc_x": 0.0105, "acc_y": 0.98, "acc_z": 0.13, "gy_x": 0.218, "gy_y": -0.4987, "gy_z": -0.3869, "timestamp": "1676156092.2375"}, {"acc_x": 0.0015, "acc_y": 0.98, "acc_z": 0.13, "gy_x": 0.0329, "gy_y": -0.8271, "gy_z": -0.6359, "timestamp": "1676156092.25"}, {"acc_x": 0.01, "acc_y": 0.98, "acc_z": 0.13, "gy_x": 0.2977, "gy_y": -0.638, "gy_z": -0.4807, "timestamp": "1676156092.2625"}, {"acc_x": 0.0151, "acc_y": 0.98, "acc_z": 0.1351, "gy_x": 0.5269, "gy_y": -0.7496, "gy_z": -0.4435, "timestamp": "1676156092.275"}, {"acc_x": 0.0365, "acc_y": 0.98, "acc_z": 0.14, "gy_x": 0.2382, "gy_y": -0.8288, "gy_z": -0.4724, "timestamp": "1676156092.2875"}, {"acc_x": 0.04, "acc_y": 0.98, "acc_z": 0.14, "gy_x": 0.0881, "gy_y": -0.8181, "gy_z": -0.43, "timestamp": "1676156092.3"}, {"acc_x": 0.037, "acc_y": 0.98, "acc_z": 0.14, "gy_x": 0.3221, "gy_y": -0.7664, "gy_z": -0.3445, "timestamp": "1676156092.3125"}, {"acc_x": 0.03, "acc_y": 0.98, "acc_z": 0.14, "gy_x": 0.2151, "gy_y": -0.92, "gy_z": -0.5054, "timestamp": "1676156092.325"}, {"acc_x": 0.0217, "acc_y": 0.98, "acc_z": 0.1317, "gy_x": 0.4546, "gy_y": -0.92, "gy_z": -0.5443, "timestamp": "1676156092.3375"}, {"acc_x": 0.02, "acc_y": 0.98, "acc_z": 0.1284, "gy_x": 0.6658, "gy_y": -0.4963, "gy_z": -0.4279, "timestamp": "1676156092.35"}, {"acc_x": 0.02, "acc_y": 0.98, "acc_z": 0.12, "gy_x": 0.5908, "gy_y": -0.6088, "gy_z": -0.3904, "timestamp": "1676156092.3625"}, {"acc_x": 0.02, "acc_y": 0.98, "acc_z": 0.12, "gy_x": 0.5802, "gy_y": -0.6099, "gy_z": -0.3999, "timestamp": "1676156092.375"}, {"acc_x": 0.02, "acc_y": 0.98, "acc_z": 0.12, "gy_x": 0.4428, "gy_y": -0.6943, "gy_z": -0.49, "timestamp": "1676156092.3875"}, {"acc_x": 0.02, "acc_y": 0.98, "acc_z": 0.13, "gy_x": 0.4308, "gy_y": -0.9204, "gy_z": -0.43, "timestamp": "1676156092.4"}, {"acc_x": 0.02, "acc_y": 0.98, "acc_z": 0.13, "gy_x": 0.8278, "gy_y": -1.0852, "gy_z": -0.43, "timestamp": "1676156092.4125"}, {"acc_x": 0.02, "acc_y": 0.98, "acc_z": 0.13, "gy_x": 0.7152, "gy_y": -1.0101, "gy_z": -0.43, "timestamp": "1676156092.425"}, {"acc_x": 0.02, "acc_y": 0.98, "acc_z": 0.1387, "gy_x": 0.5361, "gy_y": -1.1043, "gy_z": -0.49, "timestamp": "1676156092.4375"}, {"acc_x": 0.02, "acc_y": 0.98, "acc_z": 0.14, "gy_x": 0.4215, "gy_y": -1.1279, "gy_z": -0.49, "timestamp": "1676156092.45"}, {"acc_x": 0.02, "acc_y": 0.98, "acc_z": 0.14, "gy_x": 0.7096, "gy_y": -1.1, "gy_z": -0.3582, "timestamp": "1676156092.4625"}, {"acc_x": 0.02, "acc_y": 0.98, "acc_z": 0.14, "gy_x": 0.49, "gy_y": -1.1335, "gy_z": -0.4732, "timestamp": "1676156092.475"}, {"acc_x": 0.02, "acc_y": 0.98, "acc_z": 0.148, "gy_x": 0.49, "gy_y": -1.2119, "gy_z": -0.434, "timestamp": "1676156092.4875"}, {"acc_x": 0.02, "acc_y": 0.98, "acc_z": 0.15, "gy_x": 0.4217, "gy_y": -1.3869, "gy_z": -0.61, "timestamp": "1676156092.5"}, {"acc_x": 0.02, "acc_y": 0.98, "acc_z": 0.1466, "gy_x": 0.3025, "gy_y": -1.1987, "gy_z": -0.61, "timestamp": "1676156092.5125"}, {"acc_x": 0.02, "acc_y": 0.98, "acc_z": 0.14, "gy_x": 0.2802, "gy_y": -1.067, "gy_z": -0.523, "timestamp": "1676156092.525"}, {"acc_x": 0.0114, "acc_y": 0.98, "acc_z": 0.14, "gy_x": 0.1109, "gy_y": -0.9593, "gy_z": -0.55, "timestamp": "1676156092.5375"}, {"acc_x": 0.02, "acc_y": 0.98, "acc_z": 0.14, "gy_x": 0.3102, "gy_y": -0.7904, "gy_z": -0.4302, "timestamp": "1676156092.55"}, {"acc_x": 0.0236, "acc_y": 0.98, "acc_z": 0.14, "gy_x": 0.434, "gy_y": -0.92, "gy_z": -0.49, "timestamp": "1676156092.5625"}, {"acc_x": 0.0361, "acc_y": 0.98, "acc_z": 0.14, "gy_x": 0.6595, "gy_y": -0.92, "gy_z": -0.49, "timestamp": "1676156092.575"}, {"acc_x": 0.04, "acc_y": 0.98, "acc_z": 0.14, "gy_x": 0.3359, "gy_y": -0.9329, "gy_z": -0.5841, "timestamp": "1676156092.5875"}, {"acc_x": 0.02, "acc_y": 0.98, "acc_z": 0.1386, "gy_x": 0.1386, "gy_y": -1.0859, "gy_z": -0.5436, "timestamp": "1676156092.6"}, {"acc_x": 0.0168, "acc_y": 0.98, "acc_z": 0.1332, "gy_x": 0.5458, "gy_y": -1.1128, "gy_z": -0.4085, "timestamp": "1676156092.6125"}, {"acc_x": 0.0159, "acc_y": 0.98, "acc_z": 0.14, "gy_x": 0.2773, "gy_y": -1.16, "gy_z": -0.55, "timestamp": "1676156092.625"}, {"acc_x": 0.02, "acc_y": 0.98, "acc_z": 0.14, "gy_x": 0.1929, "gy_y": -1.16, "gy_z": -0.55, "timestamp": "1676156092.6375"}, {"acc_x": 0.0211, "acc_y": 0.98, "acc_z": 0.1411, "gy_x": 0.2415, "gy_y": -0.9203, "gy_z": -0.6694, "timestamp": "1676156092.65"}, {"acc_x": 0.03, "acc_y": 0.98, "acc_z": 0.15, "gy_x": 0.4339, "gy_y": -0.9575, "gy_z": -0.5949, "timestamp": "1676156092.6625"}, {"acc_x": 0.024, "acc_y": 0.98, "acc_z": 0.15, "gy_x": 0.45, "gy_y": -0.8814, "gy_z": -0.4569, "timestamp": "1676156092.675"}, {"acc_x": 0.02, "acc_y": 0.98, "acc_z": 0.15, "gy_x": 0.3846, "gy_y": -0.9054, "gy_z": -0.4811, "timestamp": "1676156092.6875"}, {"acc_x": 0.02, "acc_y": 0.98, "acc_z": 0.15, "gy_x": 0.0401, "gy_y": -0.993, "gy_z": -0.5565, "timestamp": "1676156092.7"}, {"acc_x": 0.02, "acc_y": 0.98, "acc_z": 0.15, "gy_x": 0.3532, "gy_y": -1.6055, "gy_z": -0.5055, "timestamp": "1676156092.7125"}, {"acc_x": 0.0253, "acc_y": 0.98, "acc_z": 0.15, "gy_x": 0.267, "gy_y": -1.6851, "gy_z": -0.5851, "timestamp": "1676156092.725"}, {"acc_x": 0.03, "acc_y": 0.98, "acc_z": 0.1582, "gy_x": 0.3135, "gy_y": -1.6938, "gy_z": -0.5609, "timestamp": "1676156092.7375"}, {"acc_x": 0.02, "acc_y": 0.9786, "acc_z": 0.16, "gy_x": 0.2968, "gy_y": -1.7514, "gy_z": -0.5838, "timestamp": "1676156092.75"}, {"acc_x": 0.02, "acc_y": 0.9731, "acc_z": 0.16, "gy_x": 0.4014, "gy_y": -1.6957, "gy_z": -0.6272, "timestamp": "1676156092.7625"}, {"acc_x": 0.0259, "acc_y": 0.98, "acc_z": 0.16, "gy_x": 0.2555, "gy_y": -1.5096, "gy_z": -0.5072, "timestamp": "1676156092.775"}, {"acc_x": 0.0376, "acc_y": 0.9876, "acc_z": 0.1676, "gy_x": 0.1362, "gy_y": -1.2018, "gy_z": -0.5449, "timestamp": "1676156092.7875"}, {"acc_x": 0.02, "acc_y": 0.97, "acc_z": 0.1624, "gy_x": 0.191, "gy_y": -0.9168, "gy_z": -0.43, "timestamp": "1676156092.8"}, {"acc_x": 0.02, "acc_y": 0.9732, "acc_z": 0.1703, "gy_x": 1.0203, "gy_y": -0.6771, "gy_z": -0.43, "timestamp": "1676156092.8125"}, {"acc_x": 0.0145, "acc_y": 0.98, "acc_z": 0.161, "gy_x": 0.1626, "gy_y": -0.7159, "gy_z": -0.49, "timestamp": "1676156092.825"}, {"acc_x": 0.0188, "acc_y": 0.9712, "acc_z": 0.1612, "gy_x": 0.2515, "gy_y": -0.4156, "gy_z": -0.3816, "timestamp": "1676156092.8375"}, {"acc_x": 0.0304, "acc_y": 0.9796, "acc_z": 0.17, "gy_x": -0.185, "gy_y": 0.0864, "gy_z": -0.12, "timestamp": "1676156092.85"}, {"acc_x": 0.0332, "acc_y": 0.9734, "acc_z": 0.1768, "gy_x": 1.0598, "gy_y": 0.7703, "gy_z": -0.1299, "timestamp": "1676156092.8625"}, {"acc_x": 0.02, "acc_y": 0.98, "acc_z": 0.1843, "gy_x": 0.2401, "gy_y": 0.6969, "gy_z": -0.1666, "timestamp": "1676156092.875"}, {"acc_x": 0.0117, "acc_y": 0.9717, "acc_z": 0.1883, "gy_x": 1.1283, "gy_y": 0.9532, "gy_z": -0.1632, "timestamp": "1676156092.8875"}, {"acc_x": 0.0194, "acc_y": 0.9777, "acc_z": 0.1823, "gy_x": 0.9146, "gy_y": 1.1, "gy_z": -0.21, "timestamp": "1676156092.9"}, {"acc_x": 0.0063, "acc_y": 0.9437, "acc_z": 0.2126, "gy_x": 0.6312, "gy_y": 1.4438, "gy_z": 0.0113, "timestamp": "1676156092.9125"}, {"acc_x": 0.0184, "acc_y": 0.9561, "acc_z": 0.2122, "gy_x": 0.7822, "gy_y": 1.5215, "gy_z": -0.0861, "timestamp": "1676156092.925"}, {"acc_x": 0.03, "acc_y": 0.96, "acc_z": 0.2034, "gy_x": 0.6197, "gy_y": 1.8127, "gy_z": -0.0048, "timestamp": "1676156092.9375"}, {"acc_x": 0.0315, "acc_y": 0.9985, "acc_z": 0.2085, "gy_x": 0.18, "gy_y": 2.0844, "gy_z": 0.0089, "timestamp": "1676156092.95"}, {"acc_x": 0.0427, "acc_y": 0.9763, "acc_z": 0.1937, "gy_x": 0.18, "gy_y": 2.1635, "gy_z": 0.1671, "timestamp": "1676156092.9625"}, {"acc_x": 0.0181, "acc_y": 0.9819, "acc_z": 0.2238, "gy_x": 0.2884, "gy_y": 2.868, "gy_z": 0.12, "timestamp": "1676156092.975"}, {"acc_x": 0.001, "acc_y": 0.981, "acc_z": 0.1228, "gy_x": -1.5604, "gy_y": 2.4569, "gy_z": 0.0961, "timestamp": "1676156092.9875"}, {"acc_x": 0.02, "acc_y": 1.01, "acc_z": 0.25, "gy_x": 1.2197, "gy_y": 3.9698, "gy_z": 0.0, "timestamp": "1676156093.0"}, {"acc_x": -0.0041, "acc_y": 0.9662, "acc_z": 0.1927, "gy_x": 0.4254, "gy_y": 3.2481, "gy_z": 0.2514, "timestamp": "1676156093.0125"}, {"acc_x": 0.0554, "acc_y": 0.9464, "acc_z": 0.1543, "gy_x": 2.3195, "gy_y": 4.0209, "gy_z": 0.2957, "timestamp": "1676156093.025"}, {"acc_x": 0.06, "acc_y": 0.981, "acc_z": 0.1043, "gy_x": -3.1321, "gy_y": 2.2427, "gy_z": 0.1753, "timestamp": "1676156093.0375"}, {"acc_x": 0.0358, "acc_y": 0.9985, "acc_z": 0.1912, "gy_x": -2.0103, "gy_y": 2.1734, "gy_z": 0.2778, "timestamp": "1676156093.05"}, {"acc_x": 0.0568, "acc_y": 0.9768, "acc_z": 0.1301, "gy_x": 1.8846, "gy_y": 3.2252, "gy_z": 0.3406, "timestamp": "1676156093.0625"}, {"acc_x": 0.0244, "acc_y": 0.9612, "acc_z": 0.1605, "gy_x": 4.8308, "gy_y": 3.6868, "gy_z": 0.2588, "timestamp": "1676156093.075"}]